Workbook

Sheet Inputs
A1: Tidebound revenue model - inputs
A2: Blue cells are inputs (copied from shared/config/catalog.json; edit here to explore). Yellow = key assumptions. Black cells are formulas.
A4: Daily players (DAU) | B4: 10000
A6: Products
A7: Product | B7: Price (USD) | C7: Monthly buy rate | D7: Robux price | E7: Spend per DAU ($) | F7: Store type
A8: gems_handful | B8: 0.99 | C8: 0 | D8: =ROUND(B8/$B$28,0) -> 99 | E8: =B8*C8 -> 0 | F8: developerProduct
A9: gems_pouch | B9: 4.99 | C9: 0 | D9: =ROUND(B9/$B$28,0) -> 499 | E9: =B9*C9 -> 0 | F9: developerProduct
A10: gems_chest | B10: 9.99 | C10: 0 | D10: =ROUND(B10/$B$28,0) -> 999 | E10: =B10*C10 -> 0 | F10: developerProduct
A11: gems_hoard | B11: 19.99 | C11: 0 | D11: =ROUND(B11/$B$28,0) -> 1999 | E11: =B11*C11 -> 0 | F11: developerProduct
A12: gems_vault | B12: 49.99 | C12: 0 | D12: =ROUND(B12/$B$28,0) -> 4999 | E12: =B12*C12 -> 0 | F12: developerProduct
A13: starter_pack | B13: 2.99 | C13: 0.01 | D13: =ROUND(B13/$B$28,0) -> 299 | E13: =B13*C13 -> 0.0299 | F13: gamePass
A14: cosmetic_crate | B14: 1.99 | C14: 0.012 | D14: =ROUND(B14/$B$28,0) -> 199 | E14: =B14*C14 -> 0.02388 | F14: developerProduct
A15: harbor_pass | B15: 4.99 | C15: 0.008 | D15: =ROUND(B15/$B$28,0) -> 499 | E15: =B15*C15 -> 0.03992 | F15: developerProduct
A16: harbor_club | B16: 4.99 | C16: 0.005 | D16: =ROUND(B16/$B$28,0) -> 499 | E16: =B16*C16 -> 0.02495 | F16: subscription
A17: storage_pass | B17: 7.99 | C17: 0.004 | D17: =ROUND(B17/$B$28,0) -> 799 | E17: =B17*C17 -> 0.03196 | F17: gamePass
A19: Standalone app platform fees
A20: iOS commission (Small Business Program) | B20: 0.15
A21: Google Play rate, first $1M per year | B21: 0.15
A22: Google Play rate above $1M per year | B22: 0.3
A23: Google Play threshold ($ per year) | B23: 1000000
A24: Platform mix: iOS share of spend | B24: 0.5
A25: Platform mix: Google share of spend | B25: 0.5
A27: Roblox payouts
A28: USD per Robux (price mapping) | B28: 0.01
A29: Roblox platform fee | B29: 0.3
A30: DevEx cash-out ($ per earned Robux) | B30: 0.0038
A31: Premium payouts ($ per DAU per month) | B31: 0
A33: Fixed monthly costs
A34: Standalone: backend | B34: 400
A35: Standalone: marketing | B35: 1000
A36: Roblox: companion backend | B36: 0
A37: Roblox: marketing (sponsored ads) | B37: 0

Sheet Model
A1: Tidebound revenue model - outputs (all formulas)
A3: Metric | B3: Standalone app | C3: Roblox | D3: Formula
A5: Daily players | B5: =Inputs!$B$4 -> 10000 | C5: =Inputs!$B$4 -> 10000 | D5: Input
A6: Spend per daily player per month | B6: =SUM(Inputs!$E$8:$E$17) -> 0.15061 | C6: =SUM(Inputs!$E$8:$E$17) -> 0.15061 | D6: Sum of price x monthly buy rate
A7: Gross monthly player spend | B7: =B5*B6 -> 1506.1 | C7: =C5*C6 -> 1506.1 | D7: DAU x spend per DAU
A8: Gross annual player spend | B8: =B7*12 -> 18073.2 | C8: =C7*12 -> 18073.2 | D8: Monthly x 12
A9: Google Play rate applied | B9: =IF(B8*Inputs!$B$25>Inputs!$B$23,Inputs!$B$22,Inputs!$B$21) -> 0.15 | D9: 15% until Google spend passes $1M/year
A10: Platform share of spend | B10: =Inputs!$B$20*Inputs!$B$24+B9*Inputs!$B$25 -> 0.15 | C10: =1-C11 -> 0.734 | D10: Standalone: blended store fee. Roblox: 1 - keep rate
A11: Developer keep rate | B11: =1-B10 -> 0.85 | C11: =(1-Inputs!$B$29)*Inputs!$B$30/Inputs!$B$28 -> 0.266 | D11: Roblox: (1 - 30%) x DevEx $ per Robux / $ per Robux
A12: Platform fee ($ per month) | B12: =B7*B10 -> 225.915 | C12: =C7*C10 -> 1105.4774 | D12: Gross x platform share
A13: Premium Payouts ($ per month) | B13: =0 -> 0 | C13: =Inputs!$B$31*C5 -> 0 | D13: Roblox only
A14: Net revenue per month | B14: =B7-B12+B13 -> 1280.185 | C14: =C7-C12+C13 -> 400.6226 | D14: Gross - fee + payouts
A15: Net revenue per year | B15: =B14*12 -> 15362.22 | C15: =C14*12 -> 4807.4712 | D15: Monthly x 12
A16: Fixed costs per month | B16: =Inputs!$B$34+Inputs!$B$35 -> 1400 | C16: =Inputs!$B$36+Inputs!$B$37 -> 0 | D16: Backend + marketing
A17: Profit per month | B17: =B14-B16 -> -119.815 | C17: =C14-C16 -> 400.6226 | D17: Net - fixed costs
A18: Profit per year | B18: =B17*12 -> -1437.78 | C18: =C17*12 -> 4807.4712 | D18: Monthly x 12
A19: Net margin per daily player per month | B19: =B6*B11 -> 0.1280185 | C19: =C6*C11+Inputs!$B$31 -> 0.04006226 | D19: Spend per DAU x keep rate (+ payouts)
A20: Break-even daily players | B20: =IF(B19>0,B16/B19,0) -> 10935.919 | C20: =IF(C19>0,C16/C19,0) -> 0 | D20: Fixed costs / margin per DAU
A22: Crossover: daily players where standalone profit overtakes Roblox | B22: =IF(B19>C19,(B16-C16)/(B19-C19),0) -> 15917.006 | D22: (Standalone fixed - Roblox fixed) / (standalone margin - Roblox margin)
A24: Planning check (numbers from the brief)
B25: Brief | C25: Model | D25: Difference
A26: Spend per daily player per month | B26: 0.15 | C26: =B6 -> 0.15061 | D26: =C26-B26 -> 0.00061
A27: Gross per month at 10,000 DAU | B27: 1506 | C27: =B7 -> 1506.1 | D27: =C27-B27 -> 0.1
A28: Net of 15% store cut per month | B28: 1280 | C28: =B14 -> 1280.185 | D28: =C28-B28 -> 0.185
A29: Fixed costs per month | B29: 1400 | C29: =B16 -> 1400 | D29: =C29-B29 -> 0
A30: Standalone break-even DAU | B30: 11000 | C30: =B20 -> 10935.919 | D30: =C30-B30 -> -64.080582
A31: Roblox keep rate | B31: 0.27 | C31: =C11 -> 0.266 | D31: =C31-B31 -> -0.004
A32: Crossover DAU | B32: 16000 | C32: =B22 -> 15917.006 | D32: =C32-B32 -> -82.993998
A34: Differences: break-even is 10,936 (brief rounds to ~11,000); Roblox keep is 26.6% (0.7 x 0.0038 / 0.01; brief rounds to 27%); crossover is ~15,900 (brief ~16,000) and assumes Roblox has no fixed costs.

Sheet Scenarios
A1: Profit by daily players (uses Model and Inputs)
A3: Daily players | B3: Gross / month | C3: Standalone profit / month | D3: Roblox profit / month | E3: Better option
A4: 1000 | B4: =A4*Model!$B$6 -> 150.61 | C4: =B4*Model!$B$11-Model!$B$16 -> -1271.9815 | D4: =B4*Model!$C$11+A4*Inputs!$B$31-Model!$C$16 -> 40.06226 | E4: =IF(C4>D4,"Standalone","Roblox") -> Roblox
A5: 2500 | B5: =A5*Model!$B$6 -> 376.525 | C5: =B5*Model!$B$11-Model!$B$16 -> -1079.9537 | D5: =B5*Model!$C$11+A5*Inputs!$B$31-Model!$C$16 -> 100.15565 | E5: =IF(C5>D5,"Standalone","Roblox") -> Roblox
A6: 5000 | B6: =A6*Model!$B$6 -> 753.05 | C6: =B6*Model!$B$11-Model!$B$16 -> -759.9075 | D6: =B6*Model!$C$11+A6*Inputs!$B$31-Model!$C$16 -> 200.3113 | E6: =IF(C6>D6,"Standalone","Roblox") -> Roblox
A7: 7500 | B7: =A7*Model!$B$6 -> 1129.575 | C7: =B7*Model!$B$11-Model!$B$16 -> -439.86125 | D7: =B7*Model!$C$11+A7*Inputs!$B$31-Model!$C$16 -> 300.46695 | E7: =IF(C7>D7,"Standalone","Roblox") -> Roblox
A8: 10000 | B8: =A8*Model!$B$6 -> 1506.1 | C8: =B8*Model!$B$11-Model!$B$16 -> -119.815 | D8: =B8*Model!$C$11+A8*Inputs!$B$31-Model!$C$16 -> 400.6226 | E8: =IF(C8>D8,"Standalone","Roblox") -> Roblox
A9: 12500 | B9: =A9*Model!$B$6 -> 1882.625 | C9: =B9*Model!$B$11-Model!$B$16 -> 200.23125 | D9: =B9*Model!$C$11+A9*Inputs!$B$31-Model!$C$16 -> 500.77825 | E9: =IF(C9>D9,"Standalone","Roblox") -> Roblox
A10: 15000 | B10: =A10*Model!$B$6 -> 2259.15 | C10: =B10*Model!$B$11-Model!$B$16 -> 520.2775 | D10: =B10*Model!$C$11+A10*Inputs!$B$31-Model!$C$16 -> 600.9339 | E10: =IF(C10>D10,"Standalone","Roblox") -> Roblox
A11: 16000 | B11: =A11*Model!$B$6 -> 2409.76 | C11: =B11*Model!$B$11-Model!$B$16 -> 648.296 | D11: =B11*Model!$C$11+A11*Inputs!$B$31-Model!$C$16 -> 640.99616 | E11: =IF(C11>D11,"Standalone","Roblox") -> Standalone
A12: 20000 | B12: =A12*Model!$B$6 -> 3012.2 | C12: =B12*Model!$B$11-Model!$B$16 -> 1160.37 | D12: =B12*Model!$C$11+A12*Inputs!$B$31-Model!$C$16 -> 801.2452 | E12: =IF(C12>D12,"Standalone","Roblox") -> Standalone
A13: 25000 | B13: =A13*Model!$B$6 -> 3765.25 | C13: =B13*Model!$B$11-Model!$B$16 -> 1800.4625 | D13: =B13*Model!$C$11+A13*Inputs!$B$31-Model!$C$16 -> 1001.5565 | E13: =IF(C13>D13,"Standalone","Roblox") -> Standalone
A14: 30000 | B14: =A14*Model!$B$6 -> 4518.3 | C14: =B14*Model!$B$11-Model!$B$16 -> 2440.555 | D14: =B14*Model!$C$11+A14*Inputs!$B$31-Model!$C$16 -> 1201.8678 | E14: =IF(C14>D14,"Standalone","Roblox") -> Standalone
A15: 40000 | B15: =A15*Model!$B$6 -> 6024.4 | C15: =B15*Model!$B$11-Model!$B$16 -> 3720.74 | D15: =B15*Model!$C$11+A15*Inputs!$B$31-Model!$C$16 -> 1602.4904 | E15: =IF(C15>D15,"Standalone","Roblox") -> Standalone
... A18: 100000 | B18: =A18*Model!$B$6 -> 15061 | C18: =B18*Model!$B$11-Model!$B$16 -> 11401.85 | D18: =B18*Model!$C$11+A18*Inputs!$B$31-Model!$C$16 -> 4006.226 | E18: =IF(C18>D18,"Standalone","Roblox") -> Standalone

Sheet Notes
A1: How to use: change blue cells on Inputs. Every output on Model and Scenarios recalculates.
A2: Source of defaults: shared/config/catalog.json (prices, buy rates, fees, Roblox mapping, costs). Regenerate with python3 model/build_model.py after editing config.
A3: Gem bundles have no planning buy rate in the brief, so they contribute 0 by default. Add rates on Inputs to include them.
A4: Roblox keep rate = (1 - platform fee) x DevEx rate / USD per Robux = 0.7 x 0.0038 / 0.01 = 26.6% of player spend.
A5: Roblox Subscriptions pay out differently from Robux sales; the model applies the same keep rate to Harbor Club. Check the current Roblox subscription payout terms before relying on it.
A6: The brief's crossover (~16,000 DAU) assumes Roblox has no fixed costs. With the same $1,000 marketing on both, the crossover falls to about 4,500 DAU (see Inputs Roblox costs).
A7: Tidebound ships on Roblox. With $1,000/month marketing on Roblox, break-even there is about 25,000 DAU at the planning buy rates.
